napari_ft/__init__.py
napari_ft/_version.py
napari_ft/_widget.py
napari_ft/napari.yaml
napari_ft-0.1.0.dist-info/licenses/LICENSE
napari_ft-0.1.0.dist-info/METADATA
napari_ft-0.1.0.dist-info/WHEEL
napari_ft-0.1.0.dist-info/entry_points.txt
napari_ft-0.1.0.dist-info/top_level.txt
napari_ft-0.1.0.dist-info/RECORD
